runit/Request.py
runit/__init__.py
runit/cli.py
runit/constants.py
runit/core.py
runit/exceptions.py
runit/generate.py
runit/runit.py
runit/test.py
runit/languages/__init__.py
runit/languages/javascript.py
runit/languages/multi.py
runit/languages/php.py
runit/languages/python.py
runit/languages/runtime.py
runit/modules/__init__.py
runit/modules/account.py
runit/plugins/__init__.py
runit/plugins/base.py
runit/plugins/languages/__init__.py
runit/plugins/languages/javascript.py
runit/plugins/languages/language.py
runit/plugins/languages/php.py
runit/plugins/languages/python.py
runit/plugins/languages/r.py
runit/templates/.runitignore
runit/templates/404.html
runit/templates/request.php
runit/templates/runit.json
runit/templates/javascript/main.js
runit/templates/javascript/package.json
runit/templates/multi/application.py
runit/templates/multi/composer.json
runit/templates/multi/index.php
runit/templates/multi/main.js
runit/templates/multi/package.json
runit/templates/multi/request.php
runit/templates/multi/requirements.txt
runit/templates/php/composer.json
runit/templates/php/index.php
runit/templates/python/application.py
runit/templates/python/requirements.txt
runit/tools/javascript/loader.js
runit/tools/javascript/runner.js
runit/tools/php/loader.php
runit/tools/php/manager.php
runit/tools/php/runner.php
runit/tools/python/loader.py
runit/tools/python/runner.py
runit_cli-0.4.3.dist-info/METADATA
runit_cli-0.4.3.dist-info/WHEEL
runit_cli-0.4.3.dist-info/entry_points.txt
runit_cli-0.4.3.dist-info/top_level.txt
runit_cli-0.4.3.dist-info/RECORD
