Metadata-Version: 2.1
Name: runit-cli
Version: 0.4.3
Summary: Develop serverless applications
Author: Amos Amissah
Author-email: theonlyamos@gmail.com
Project-URL: Source, https://github.com/theonlyamos/runit
Project-URL: Tracker, https://github.com/theonlyamos/runit/issues
Keywords: python3 runit developer serverless architecture docker
Classifier: Development Status :: 3 - Alpha
Classifier: Intended Audience :: Developers
Classifier: Topic :: Software Development :: Build Tools
Classifier: License :: OSI Approved :: MIT License
Classifier: Programming Language :: Python :: 3
Classifier: Programming Language :: Python :: 3.6
Classifier: Programming Language :: Python :: 3.7
Classifier: Programming Language :: Python :: 3.8
Classifier: Programming Language :: Python :: 3.9
Classifier: Programming Language :: Python :: 3.10
Classifier: Programming Language :: Python :: 3.11
Classifier: Programming Language :: Python :: 3.12
Requires-Dist: requests
Requires-Dist: python-dotenv
Requires-Dist: fastapi
Requires-Dist: passlib
Requires-Dist: docker
Requires-Dist: uvicorn
Requires-Dist: websockets
